saudi_id_validator/__init__.py
saudi_id_validator/validate_id.py
saudi_ids_validator-0.0.1.dist-info/LICENSE
saudi_ids_validator-0.0.1.dist-info/METADATA
saudi_ids_validator-0.0.1.dist-info/WHEEL
saudi_ids_validator-0.0.1.dist-info/top_level.txt
saudi_ids_validator-0.0.1.dist-info/RECORD
