Metadata-Version: 2.1
Name: saudi-ids-validator
Version: 0.0.1
Summary: A tiny package that helps you validate Saudi national or iqama ids
Home-page: https://github.com/malzaid0/saudi-id-validator-pypi/
Author: Mohammed Alzaid
Author-email: m7md.alzaid5@gmail.com
License: UNKNOWN
Project-URL: Bug Reports, https://github.com/malzaid0/saudi-id-validator-pypi/issues
Project-URL: Source, https://github.com/malzaid0/saudi-id-validator-pypi/
Keywords: saudi,saudi national,iqama,saudi id,saudi arabia,saudi id validator
Platform: UNKNOWN
Classifier: Programming Language :: Python :: 3
Classifier: License :: OSI Approved :: MIT License
Classifier: Operating System :: OS Independent
License-File: LICENSE
